wave_bwf_rf64/__init__.py
wave_bwf_rf64/chunk.py
wave_bwf_rf64/wave.py
wave_bwf_rf64-2.0.1.dist-info/METADATA
wave_bwf_rf64-2.0.1.dist-info/WHEEL
wave_bwf_rf64-2.0.1.dist-info/licenses/LICENSE
wave_bwf_rf64-2.0.1.dist-info/RECORD
