Metadata-Version: 2.1
Name: wave-bwf-rf64
Version: 2.0.1
Summary: Python modules for handling the Broadcast Wave Format and RF64 files.
Project-URL: Homepage, https://github.com/nrkno/wave-bwf-rf64/
Project-URL: Changelog, https://github.com/nrkno/wave-bwf-rf64/blob/main/CHANGELOG.md
License:                     GNU GENERAL PUBLIC LICENSE
License-File: LICENSE
Classifier: Development Status :: 4 - Beta
Classifier: License :: OSI Approved :: GNU General Public License v3 or later (GPLv3+)
Classifier: Operating System :: OS Independent
Classifier: Programming Language :: Python :: 3.10
Classifier: Programming Language :: Python :: 3.11
Classifier: Topic :: Multimedia :: Sound/Audio
Requires-Python: >=3.10
